{
  "type": "FeatureCollection",
  "features": [
    {
      "type": "Feature",
      "properties": {
        "name": "Basque",
        "native_name": "Euskara",
        "family": "Isolate",
        "branch": "None (Isolate)",
        "type_of_lect": "Language",
        "color": "#e74c3c",
        "is_official": false,
        "kind": "point",
        "wikipedia_link": "https://en.wikipedia.org/wiki/Basque_language"
      },
      "geometry": {
        "type": "Point",
        "coordinates": [-2.472694, 42.947778]
      }
    },   
    {
      "type": "Feature",
      "properties": {
        "name": "Rusyn",
        "native_name": "Русиньскый язык",
        "family": "Indo-European",
        "branch": "East Slavic",
        "type_of_lect": "Language",
        "color": "#3498db",
        "is_official": false,
        "kind": "point",
        "wikipedia_link": "https://en.wikipedia.org/wiki/Rusyn_language"
      },
      "geometry": {
        "type": "Point",
        "coordinates": [22.187206, 49.065949]
      }
    },
    {
      "type": "Feature",
      "properties": {
        "name": "Slovak",
        "native_name": "Slovenský",
        "family": "Indo-European",
        "branch": "West Slavic",
        "type_of_lect": "Language",
        "color": "#3498db",
        "is_official": true,
        "kind": "point",
        "wikipedia_link": "https://en.wikipedia.org/wiki/Slovak_language"
      },
      "geometry": {
        "type": "Point",
        "coordinates": [19.282193, 48.631457]
      }
    },
    {
      "type": "Feature",
      "properties": {
        "name": "TshiVenda",
        "native_name": "Tshivenḓa",
        "family": "Niger-Congo",
        "branch": "Bantu",
        "type_of_lect": "Language",
        "color": "#2ecc71",
        "is_official": true,
        "kind": "point",
        "wikipedia_link": "https://en.wikipedia.org/wiki/Venda_language"
      },
      "geometry": {
        "type": "Point",
        "coordinates": [31.000273, -22.589415]
      }
    }
  ]
}
